biotdg/__init__.py
biotdg-0.1.0.dist-info/LICENSE
biotdg-0.1.0.dist-info/METADATA
biotdg-0.1.0.dist-info/WHEEL
biotdg-0.1.0.dist-info/entry_points.txt
biotdg-0.1.0.dist-info/top_level.txt
biotdg-0.1.0.dist-info/RECORD
