Metadata-Version: 2.1
Name: biotdg
Version: 0.1.0
Summary: Bioinformatics Test Data Generator
Home-page: https://github.com/biowdl/biotdg
Author: Leiden University Medical Center
Author-email: sasc@lumc.nl
License: MIT
Keywords: bioinformatics test data generator creator
Platform: UNKNOWN
Classifier: Topic :: Scientific/Engineering :: Bio-Informatics
Classifier: Programming Language :: Python :: 3 :: Only
Classifier: Programming Language :: Python :: 3
Classifier: Programming Language :: Python :: 3.6
Classifier: Programming Language :: Python :: 3.7
Classifier: License :: OSI Approved :: MIT License
Requires-Python: >=3.6,<3.8
Requires-Dist: biopython
Requires-Dist: cyvcf2
Requires-Dist: setuptools
